google_voice_parser/__init__.py
google_voice_parser/parse_google_sms.py
google_voice_parser-0.1.1.dist-info/LICENSE
google_voice_parser-0.1.1.dist-info/METADATA
google_voice_parser-0.1.1.dist-info/WHEEL
google_voice_parser-0.1.1.dist-info/entry_points.txt
google_voice_parser-0.1.1.dist-info/top_level.txt
google_voice_parser-0.1.1.dist-info/zip-safe
google_voice_parser-0.1.1.dist-info/RECORD
