Metadata-Version: 2.1
Name: google-voice-parser
Version: 0.1.1
Summary: Parse SMS from Google Voice
Home-page: https://github.com/thismachinechills/parse_google_sms
Author: thismachinechills (Alex)
Author-email: UNKNOWN
License: AGPL 3.0
Keywords: google voice,voice,sms,takeout
Platform: UNKNOWN
Requires-Dist: html-wrapper
Requires-Dist: click
